LICENSE
MANIFEST.in
README.md
setup.py
time_stamped_model/__init__.py
time_stamped_model/apps.py
time_stamped_model/models.py
time_stamped_model.egg-info/PKG-INFO
time_stamped_model.egg-info/SOURCES.txt
time_stamped_model.egg-info/dependency_links.txt
time_stamped_model.egg-info/top_level.txt