Metadata-Version: 2.4
Name: time-stamped-model
Version: 0.2.12
Summary: Django app to add created and modified
Home-page: https://github.com/django-advance-utils/time-stamped-model
Author: Tom Turner
Classifier: Programming Language :: Python :: 3
Classifier: License :: OSI Approved :: MIT License
Classifier: Operating System :: OS Independent
Requires-Python: >=3.6
License-File: LICENSE
Dynamic: author
Dynamic: classifier
Dynamic: description
Dynamic: description-content-type
Dynamic: home-page
Dynamic: license-file
Dynamic: requires-python
Dynamic: summary
